pymodelio/__init__.py
pymodelio/attribute.py
pymodelio/constants.py
pymodelio/model_deserializer.py
pymodelio/model_serializer.py
pymodelio/pymodelio_meta.py
pymodelio/pymodelio_model.py
pymodelio/shared_vars.py
pymodelio/undefined.py
pymodelio/utils.py
pymodelio/decorators/__init__.py
pymodelio/decorators/deserializes.py
pymodelio/decorators/do_not_serialize.py
pymodelio/exceptions/__init__.py
pymodelio/exceptions/auto_validator_creation_exception.py
pymodelio/exceptions/model_validation_exception.py
pymodelio/settings/__init__.py
pymodelio/settings/pymodelio_setting.py
pymodelio/settings/pymodelio_settings.py
pymodelio/validators/__init__.py
pymodelio/validators/bool_validator.py
pymodelio/validators/date_validator.py
pymodelio/validators/datetime_validator.py
pymodelio/validators/default_validators_builder.py
pymodelio/validators/dict_validator.py
pymodelio/validators/email_validator.py
pymodelio/validators/float_validator.py
pymodelio/validators/forward_ref_validator.py
pymodelio/validators/int_validator.py
pymodelio/validators/iterable_validator.py
pymodelio/validators/list_validator.py
pymodelio/validators/numeric_validator.py
pymodelio/validators/set_validator.py
pymodelio/validators/string_validator.py
pymodelio/validators/tuple_validator.py
pymodelio/validators/validation_patterns.py
pymodelio/validators/validator.py
pymodelio-1.1.1.dist-info/LICENSE.txt
pymodelio-1.1.1.dist-info/METADATA
pymodelio-1.1.1.dist-info/WHEEL
pymodelio-1.1.1.dist-info/top_level.txt
pymodelio-1.1.1.dist-info/RECORD
