Metadata-Version: 2.1
Name: pymodelio
Version: 1.1.1
Summary: A simple Python module for defining rich domain models, serializing, deserializing and validating them
Home-page: https://github.com/GabrielMartinMoran/pymodelio
Author: Gabriel Martín Moran
Author-email: moran.gabriel.95@gmail.com
License-File: LICENSE.txt
Requires-Dist: ciso8601
